artc/__init__.py
artc/core.py
artc/io.py
artc/lite.py
artc/vram.py
artc-0.1.0.dist-info/METADATA
artc-0.1.0.dist-info/WHEEL
artc-0.1.0.dist-info/top_level.txt
artc-0.1.0.dist-info/RECORD
