Metadata-Version: 2.4
Name: artc
Version: 0.1.0
Summary: ARTC-LITE: Lightweight IoT Tensor Encoding for sensor data compression
Home-page: https://github.com/169B/ARTC
Author: 169B
Author-email: 169B <your.email@example.com>
License: MIT
Project-URL: Homepage, https://github.com/169B/ARTC
Project-URL: Bug Tracker, https://github.com/169B/ARTC/issues
Project-URL: Documentation, https://github.com/169B/ARTC#readme
Project-URL: Source Code, https://github.com/169B/ARTC
Keywords: compression,iot,sensors,tensor,lora,arduino,esp32,embedded
Classifier: Development Status :: 3 - Alpha
Classifier: Intended Audience :: Developers
Classifier: Intended Audience :: Science/Research
Classifier: Topic :: Scientific/Engineering
Classifier: Topic :: System :: Archiving :: Compression
Classifier: License :: OSI Approved :: MIT License
Classifier: Programming Language :: Python :: 3
Classifier: Programming Language :: Python :: 3.7
Classifier: Programming Language :: Python :: 3.8
Classifier: Programming Language :: Python :: 3.9
Classifier: Programming Language :: Python :: 3.10
Classifier: Programming Language :: Python :: 3.11
Classifier: Programming Language :: Python :: 3.12
Classifier: Operating System :: OS Independent
Requires-Python: >=3.7
Requires-Dist: numpy>=1.19.0
Provides-Extra: dev
Requires-Dist: pytest>=6.0; extra == "dev"
Requires-Dist: pytest-cov; extra == "dev"
Dynamic: author
Dynamic: home-page
Dynamic: requires-python
